ptnad_api/__init__.py
ptnad_api/__version__.py
ptnad_api/data_provider.py
ptnad_api/flow.py
ptnad_api/query.py
ptnad_api/time_tools.py
ptnad_api-0.0.1.dist-info/LICENSE
ptnad_api-0.0.1.dist-info/METADATA
ptnad_api-0.0.1.dist-info/WHEEL
ptnad_api-0.0.1.dist-info/top_level.txt
ptnad_api-0.0.1.dist-info/RECORD
